nvmath/__init__.pxd
nvmath/__init__.py
nvmath/_utils.py
nvmath/memory.py
nvmath/_internal/__init__.py
nvmath/_internal/layout.py
nvmath/_internal/templates.py
nvmath/bindings/__init__.pxd
nvmath/bindings/__init__.py
nvmath/bindings/cublas.cpython-313-aarch64-linux-gnu.so
nvmath/bindings/cublas.pxd
nvmath/bindings/cublas.pyi
nvmath/bindings/cublasLt.cpython-313-aarch64-linux-gnu.so
nvmath/bindings/cublasLt.pxd
nvmath/bindings/cublasLt.pyi
nvmath/bindings/cublasMp.cpython-313-aarch64-linux-gnu.so
nvmath/bindings/cublasMp.pxd
nvmath/bindings/cudss.cpython-313-aarch64-linux-gnu.so
nvmath/bindings/cudss.pxd
nvmath/bindings/cudss.pyi
nvmath/bindings/cufft.cpython-313-aarch64-linux-gnu.so
nvmath/bindings/cufft.pxd
nvmath/bindings/cufft.pyi
nvmath/bindings/cufftMp.cpython-313-aarch64-linux-gnu.so
nvmath/bindings/cufftMp.pxd
nvmath/bindings/cufftMp.pyi
nvmath/bindings/curand.cpython-313-aarch64-linux-gnu.so
nvmath/bindings/curand.pxd
nvmath/bindings/curand.pyi
nvmath/bindings/cusolver.cpython-313-aarch64-linux-gnu.so
nvmath/bindings/cusolver.pxd
nvmath/bindings/cusolver.pyi
nvmath/bindings/cusolverDn.cpython-313-aarch64-linux-gnu.so
nvmath/bindings/cusolverDn.pxd
nvmath/bindings/cusolverDn.pyi
nvmath/bindings/cusparse.cpython-313-aarch64-linux-gnu.so
nvmath/bindings/cusparse.pxd
nvmath/bindings/cusparse.pyi
nvmath/bindings/cutensor.cpython-313-aarch64-linux-gnu.so
nvmath/bindings/cutensor.pxd
nvmath/bindings/cutensor.pyi
nvmath/bindings/cycublas.cpython-313-aarch64-linux-gnu.so
nvmath/bindings/cycublas.pxd
nvmath/bindings/cycublasLt.cpython-313-aarch64-linux-gnu.so
nvmath/bindings/cycublasLt.pxd
nvmath/bindings/cycublasMp.cpython-313-aarch64-linux-gnu.so
nvmath/bindings/cycublasMp.pxd
nvmath/bindings/cycudss.cpython-313-aarch64-linux-gnu.so
nvmath/bindings/cycudss.pxd
nvmath/bindings/cycufft.cpython-313-aarch64-linux-gnu.so
nvmath/bindings/cycufft.pxd
nvmath/bindings/cycufftMp.cpython-313-aarch64-linux-gnu.so
nvmath_python-0.7.0.dist-info/METADATA
nvmath_python-0.7.0.dist-info/WHEEL
nvmath_python-0.7.0.dist-info/top_level.txt
nvmath_python-0.7.0.dist-info/RECORD
nvmath_python-0.7.0.dist-info/licenses/LICENSE
