Metadata-Version: 2.4
Name: nvmath-python
Version: 0.7.0
Summary: NVIDIA Math Python libraries
Author: NVIDIA Corporation
License-Expression: Apache-2.0
Classifier: Development Status :: 4 - Beta
Classifier: Intended Audience :: Developers
Classifier: Intended Audience :: Science/Research
Classifier: Intended Audience :: End Users/Desktop
Classifier: Natural Language :: English
Classifier: Operating System :: POSIX :: Linux
Classifier: Operating System :: Microsoft :: Windows
Classifier: Topic :: Education
Classifier: Topic :: Scientific/Engineering
Classifier: Topic :: Software Development :: Libraries
Classifier: Topic :: Scientific/Engineering :: Mathematics
Classifier: Programming Language :: Python :: 3 :: Only
Classifier: Programming Language :: Python :: 3.10
Classifier: Programming Language :: Python :: 3.13
Classifier: Programming Language :: Python :: 3.11
Classifier: Programming Language :: Python :: 3.12
Classifier: Programming Language :: Python :: Implementation :: CPython
Classifier: Environment :: GPU :: NVIDIA CUDA
Classifier: Environment :: GPU :: NVIDIA CUDA :: 11
Classifier: Environment :: GPU :: NVIDIA CUDA :: 12
Requires-Python: <3.14,>=3.10
License-File: LICENSE
Requires-Dist: cuda-bindings
Requires-Dist: cuda-core<0.4,>=0.3.2
Requires-Dist: cuda-pathfinder<2.0,>=1.3.2
Requires-Dist: numpy<3,>=1.25
Requires-Dist: pywin32; platform_system == "Windows"
Provides-Extra: cpu
Requires-Dist: mkl; platform_machine == "x86_64" and extra == "cpu"
Requires-Dist: nvpl-fft<1,>=0.3; (platform_system == "Linux" and platform_machine == "aarch64") and extra == "cpu"
Requires-Dist: nvpl-blas<1,>=0.3; (platform_system == "Linux" and platform_machine == "aarch64") and extra == "cpu"
Provides-Extra: sysctk12
Requires-Dist: cuda-bindings<13,>=12.9.2; extra == "sysctk12"
Requires-Dist: cutensor-cu12>=2.3.1; extra == "sysctk12"
Provides-Extra: sysctk13
Requires-Dist: cuda-bindings<14,>=13.0.1; extra == "sysctk13"
Requires-Dist: cutensor-cu13>=2.3.1; extra == "sysctk13"
Provides-Extra: cu12
Requires-Dist: nvmath-python[sysctk12]; extra == "cu12"
Requires-Dist: cuda-core[cu12]; extra == "cu12"
Requires-Dist: nvidia-cublas-cu12; extra == "cu12"
Requires-Dist: nvidia-cuda-nvrtc-cu12; extra == "cu12"
Requires-Dist: nvidia-cuda-runtime-cu12; extra == "cu12"
Requires-Dist: nvidia-cudss-cu12==0.7.*; extra == "cu12"
Requires-Dist: nvidia-cufft-cu12; extra == "cu12"
Requires-Dist: nvidia-curand-cu12; extra == "cu12"
Requires-Dist: nvidia-cusolver-cu12; extra == "cu12"
Requires-Dist: nvidia-cusparse-cu12; extra == "cu12"
Requires-Dist: cutensor-cu12>=2.3.1; extra == "cu12"
Provides-Extra: cu13
Requires-Dist: nvmath-python[sysctk13]; extra == "cu13"
Requires-Dist: cuda-core[cu13]; extra == "cu13"
Requires-Dist: cuda-toolkit[cublas,cudart,cufft,curand,cusolver,cusparse,nvrtc]==13.*; extra == "cu13"
Requires-Dist: nvidia-cudss-cu13==0.7.*; extra == "cu13"
Requires-Dist: cutensor-cu13>=2.3.1; extra == "cu13"
Provides-Extra: dx
Requires-Dist: numba; extra == "dx"
Requires-Dist: numba-cuda>=0.18.1; extra == "dx"
Provides-Extra: sysctk12-dx
Requires-Dist: nvmath-python[sysctk12]; extra == "sysctk12-dx"
Requires-Dist: nvmath-python[dx]; extra == "sysctk12-dx"
Provides-Extra: cu12-dx
Requires-Dist: nvmath-python[cu12]; extra == "cu12-dx"
Requires-Dist: nvmath-python[dx]; extra == "cu12-dx"
Requires-Dist: nvidia-libmathdx-cu12<0.3,>=0.2.3; extra == "cu12-dx"
Requires-Dist: nvidia-cuda-cccl-cu12>12.4.127; extra == "cu12-dx"
Requires-Dist: nvidia-cuda-nvrtc-cu12!=12.4.*,!=12.5.0; extra == "cu12-dx"
Provides-Extra: sysctk12-distributed
Requires-Dist: nvmath-python[sysctk12]; extra == "sysctk12-distributed"
Requires-Dist: mpi4py; extra == "sysctk12-distributed"
Requires-Dist: nvidia-nccl-cu12>=2.24.3; extra == "sysctk12-distributed"
Provides-Extra: cu12-distributed
Requires-Dist: nvmath-python[cu12]; extra == "cu12-distributed"
Requires-Dist: nvmath-python[sysctk12-distributed]; extra == "cu12-distributed"
Requires-Dist: nvidia-cublasmp-cu12>=0.6.0; extra == "cu12-distributed"
Requires-Dist: nvidia-cufftmp-cu12; extra == "cu12-distributed"
Requires-Dist: nvidia-nvshmem-cu12>=3.2.5; extra == "cu12-distributed"
Provides-Extra: sysctk13-dx
Requires-Dist: nvmath-python[sysctk13]; extra == "sysctk13-dx"
Requires-Dist: nvmath-python[dx]; extra == "sysctk13-dx"
Provides-Extra: cu13-dx
Requires-Dist: nvmath-python[cu13]; extra == "cu13-dx"
Requires-Dist: nvmath-python[dx]; extra == "cu13-dx"
Requires-Dist: nvidia-libmathdx-cu13<0.3,>=0.2.3; extra == "cu13-dx"
Requires-Dist: cuda-toolkit[cccl,nvrtc]==13.*; extra == "cu13-dx"
Provides-Extra: sysctk13-distributed
Requires-Dist: nvmath-python[sysctk13]; extra == "sysctk13-distributed"
Requires-Dist: mpi4py; extra == "sysctk13-distributed"
Requires-Dist: nvidia-nccl-cu13>=2.24.3; extra == "sysctk13-distributed"
Provides-Extra: cu13-distributed
Requires-Dist: nvmath-python[cu13]; extra == "cu13-distributed"
Requires-Dist: nvmath-python[sysctk13-distributed]; extra == "cu13-distributed"
Requires-Dist: nvidia-cublasmp-cu13>=0.6.0; extra == "cu13-distributed"
Requires-Dist: nvidia-cufftmp-cu13>=12.1.3.2; extra == "cu13-distributed"
Requires-Dist: nvidia-nvshmem-cu13>=3.2.5; extra == "cu13-distributed"
Dynamic: license-file
